dinsort.py
dinsort-0.2.dist-info/DESCRIPTION.rst
dinsort-0.2.dist-info/METADATA
dinsort-0.2.dist-info/RECORD
dinsort-0.2.dist-info/WHEEL
dinsort-0.2.dist-info/metadata.json
dinsort-0.2.dist-info/namespace_packages.txt
dinsort-0.2.dist-info/top_level.txt
