Metadata-Version: 2.0
Name: dinsort
Version: 0.2
Summary: Sort terms according to German DIN.
Home-page: https://github.com/ulif/dinsort/
Author: Uli Fouquet
Author-email: uli@gnufix.de
License: GPL 3.0
Keywords: sort terms order DIN 5007 german words
Platform: UNKNOWN
Classifier: Development Status :: 3 - Alpha
Classifier: Environment :: Console
Classifier: Intended Audience :: Developers
Classifier: Natural Language :: German
Classifier: Topic :: Utilities
Classifier: Topic :: Software Development :: Libraries :: Python Modules
Classifier: Topic :: Text Processing
Classifier: Topic :: Internet :: WWW/HTTP :: Indexing/Search
Classifier: License :: OSI Approved :: GNU General Public License v3 or later (GPLv3+)
Classifier: Programming Language :: Python :: 2
Classifier: Programming Language :: Python :: 2.7
Classifier: Programming Language :: Python :: 3
Classifier: Programming Language :: Python :: 3.4
Classifier: Programming Language :: Python :: Implementation :: CPython
Classifier: Programming Language :: Python :: Implementation :: PyPy
Requires-Dist: setuptools
Provides-Extra: docs
Requires-Dist: Sphinx; extra == 'docs'
Provides-Extra: tests
Requires-Dist: pytest (>=2.0.3); extra == 'tests'
Requires-Dist: pytest-cov; extra == 'tests'
